{
      "valid": true,
      "title": "New York Times, Monday, July 17, 2023",
      "date": "7/17/2023",
      "author": "Alexander Liebeskind",
      "editor": "Will Shortz",
      "publisher": "The New York Times",
      "copyright": "2023, The New York Times",
      "notepad": null,
      "jnotes": null,
      "key": null,
      "track": null,
      "autowrap": null,
      "mini": null,
      "id": null,
      "id2": null,
      "code": null,
      "dow": "Monday",
      "type": null,
      "target": "/Crossword?date=7/17/2023",
      "hastitle": false,
      "navigate": true,
      "hold": false,
      "auto": false,
      "uniclue": false,
      "interpretcolors": false,
      "shadecircles": false,
      "admin": false,
      "json": true,
      "size": {
            "rows": 15,
            "cols": 15
      },
      "grid": [
            "O",
            "N",
            "E",
            "S",
            "I",
            "E",
            ".",
            "B",
            "I",
            "B",
            ".",
            "C",
            "T",
            "R",
            "L",
            "K",
            "O",
            "R",
            "E",
            "A",
            "N",
            ".",
            "O",
            "R",
            "E",
            ".",
            "A",
            "R",
            "E",
            "A",
            "R",
            "U",
            "M",
            "A",
            "N",
            "D",
            "C",
            "O",
            "K",
            "E",
            ".",
            "N",
            "U",
            "N",
            "S",
            "A",
            "N",
            "A",
            "T",
            ".",
            "S",
            "I",
            "T",
            ".",
            "F",
            "E",
            "N",
            "C",
            "E",
            "S",
            ".",
            ".",
            ".",
            "B",
            "R",
            "U",
            "S",
            "H",
            "S",
            "T",
            "R",
            "O",
            "K",
            "E",
            ".",
            "S",
            "T",
            "R",
            "E",
            "E",
            "P",
            ".",
            ".",
            "T",
            "A",
            "R",
            "T",
            "S",
            ".",
            ".",
            "P",
            "A",
            "O",
            "L",
            "A",
            ".",
            "O",
            "P",
            "E",
            "C",
            ".",
            ".",
            "T",
            "B",
            "S",
            "I",
            "N",
            "S",
            "T",
            "R",
            "U",
            "C",
            "T",
            "I",
            "O",
            "N",
            "B",
            "O",
            "O",
            "K",
            "T",
            "S",
            "E",
            ".",
            ".",
            "L",
            "E",
            "A",
            "N",
            ".",
            "O",
            "O",
            "P",
            "S",
            "Y",
            ".",
            ".",
            "B",
            "I",
            "O",
            "T",
            "A",
            ".",
            ".",
            "H",
            "O",
            "R",
            "S",
            "E",
            "S",
            ".",
            "R",
            "U",
            "N",
            "N",
            "I",
            "N",
            "G",
            "J",
            "O",
            "K",
            "E",
            ".",
            ".",
            ".",
            "W",
            "I",
            "S",
            "D",
            "O",
            "M",
            ".",
            "R",
            "O",
            "T",
            ".",
            "S",
            "A",
            "S",
            "H",
            "A",
            "S",
            "H",
            "E",
            ".",
            "A",
            "R",
            "E",
            "Y",
            "O",
            "U",
            "O",
            "K",
            "A",
            "Y",
            "K",
            "E",
            "E",
            "N",
            ".",
            "T",
            "A",
            "T",
            ".",
            "I",
            "N",
            "M",
            "I",
            "N",
            "D",
            "E",
            "R",
            "S",
            "T",
            ".",
            "E",
            "T",
            "A",
            ".",
            "L",
            "I",
            "E",
            "N",
            "E",
            "E"
      ],
      "gridnums": [
            1,
            2,
            3,
            4,
            5,
            6,
            0,
            7,
            8,
            9,
            0,
            10,
            11,
            12,
            13,
            14,
            0,
            0,
            0,
            0,
            0,
            0,
            15,
            0,
            0,
            0,
            16,
            0,
            0,
            0,
            17,
            0,
            0,
            0,
            0,
            0,
            18,
            0,
            0,
            0,
            0,
            19,
            0,
            0,
            0,
            20,
            0,
            0,
            0,
            0,
            21,
            0,
            0,
            0,
            22,
            23,
            0,
            0,
            0,
            0,
            0,
            0,
            0,
            24,
            25,
            0,
            0,
            0,
            26,
            0,
            0,
            0,
            0,
            0,
            0,
            27,
            28,
            29,
            0,
            0,
            0,
            0,
            0,
            30,
            0,
            0,
            0,
            0,
            0,
            0,
            31,
            0,
            0,
            0,
            0,
            0,
            32,
            33,
            0,
            0,
            0,
            0,
            34,
            35,
            36,
            37,
            0,
            0,
            0,
            0,
            38,
            0,
            0,
            0,
            0,
            39,
            40,
            0,
            0,
            0,
            41,
            0,
            0,
            0,
            0,
            42,
            0,
            0,
            0,
            0,
            43,
            0,
            0,
            0,
            0,
            0,
            0,
            44,
            45,
            46,
            0,
            0,
            0,
            0,
            47,
            0,
            0,
            0,
            0,
            0,
            0,
            48,
            0,
            0,
            0,
            0,
            0,
            49,
            50,
            0,
            0,
            0,
            0,
            0,
            0,
            51,
            0,
            0,
            0,
            0,
            0,
            0,
            52,
            0,
            0,
            0,
            53,
            54,
            55,
            56,
            57,
            0,
            0,
            0,
            0,
            58,
            59,
            0,
            0,
            0,
            60,
            0,
            0,
            0,
            0,
            61,
            0,
            0,
            0,
            0,
            62,
            0,
            0,
            0,
            63,
            0,
            0,
            0,
            0,
            0,
            64,
            0,
            0,
            0,
            0,
            65,
            0,
            0,
            0,
            66,
            0,
            0,
            0,
            0,
            0
      ],
      "circles": null,
      "acrossmap": null,
      "downmap": null,
      "rbars": null,
      "bbars": null,
      "clues": {
            "across": [
                  "1. Baby&#39;s lightweight garment with snaps",
                  "7. Baby&#39;s dribble catcher",
                  "10. Bottom-row PC key",
                  "14. Kind of cuisine with kimchi",
                  "15. Mine cart filler",
                  "16. Length x width, for a rectangle",
                  "17. Two-ingredient drink order",
                  "19. Convent residents",
                  "20. Med school subj.",
                  "21. Use a chair",
                  "22. 2016 Denzel Washington/Viola Davis film whose title refers to real and metaphorical barriers",
                  "24. Distinctive effect of paint applied to a canvas",
                  "27. Meryl with eight Golden Globes",
                  "30. Bakery treats that are sweeter than their name suggests",
                  "31. ___ Su\u00e1rez, tennis star with eight Grand Slam doubles titles",
                  "32. Grp. with many Mideast members",
                  "34. Atlanta-based network",
                  "37. How-to manual",
                  "41. China&#39;s Mao ___-tung",
                  "42. Tilt sideways",
                  "43. &quot;___-daisy!&quot;",
                  "44. Regional flora and fauna",
                  "47. &quot;If wishes were ___, beggars would ride&quot;",
                  "48. Recurring comical reference",
                  "51. &quot;\u2026 and the ___ to know the difference&quot; (end of the Serenity Prayer)",
                  "52. Go bad",
                  "53. Pageant accessory",
                  "57. Tennis great Arthur",
                  "58. Query of concern \u2026 or a phonetic hint to two pairs of letters appearing in 17-, 24-, 37- and 48-Across",
                  "61. Sharp-witted",
                  "62. Bit of body ink",
                  "63. Under consideration",
                  "64. Once, once",
                  "65. H or \u03b7, in the Greek alphabet",
                  "66. One whose property is being held as debt security"
            ],
            "down": [
                  "1. Pod vegetable in gumbo",
                  "2. Part of speech that might be &quot;proper&quot;",
                  "3. ___ Franklin (gospel-singing sister of Aretha)",
                  "4. Icon that lights up during a turbulent plane ride",
                  "5. Writer Fleming",
                  "6. Finishes",
                  "7. Diner seating option",
                  "8. Vex",
                  "9. Meaty Mexican dish",
                  "10. Lacks what it takes",
                  "11. Service centers for big rigs",
                  "12. Zellweger who played Judy Garland in 2019&#39;s &quot;Judy&quot;",
                  "13. Glasgow gal",
                  "18. Counterpart of trans, in gender identity terminology",
                  "23. Blunder",
                  "25. Caboose&#39;s location",
                  "26. Poet Gertrude",
                  "27. Spinning skewer",
                  "28. Spends some time in the sun, maybe",
                  "29. Thorny sources of pride for a gardener",
                  "32. Atlantic or Pacific",
                  "33. Scholastic book fair org.",
                  "35. Big audio equipment brand",
                  "36. &quot;The ___ the limit&quot;",
                  "38. Frisbee sport",
                  "39. Cozy spot",
                  "40. Yawn-inducing",
                  "45. Use a tab key, say",
                  "46. Artist and musician Yoko",
                  "47. What French fries fry in",
                  "48. Staircase part",
                  "49. Environmental activist Thunberg",
                  "50. Delight",
                  "51. Boat&#39;s trail",
                  "54. Similar (to)",
                  "55. Reasonable",
                  "56. Park name in London and Chicago",
                  "59. Tell (on)",
                  "60. Informal term for college, in Great Britain"
            ]
      },
      "answers": {
            "across": [
                  "ONESIE",
                  "BIB",
                  "CTRL",
                  "KOREAN",
                  "ORE",
                  "AREA",
                  "RUMANDCOKE",
                  "NUNS",
                  "ANAT",
                  "SIT",
                  "FENCES",
                  "BRUSHSTROKE",
                  "STREEP",
                  "TARTS",
                  "PAOLA",
                  "OPEC",
                  "TBS",
                  "INSTRUCTIONBOOK",
                  "TSE",
                  "LEAN",
                  "OOPSY",
                  "BIOTA",
                  "HORSES",
                  "RUNNINGJOKE",
                  "WISDOM",
                  "ROT",
                  "SASH",
                  "ASHE",
                  "AREYOUOKAY",
                  "KEEN",
                  "TAT",
                  "INMIND",
                  "ERST",
                  "ETA",
                  "LIENEE"
            ],
            "down": [
                  "OKRA",
                  "NOUN",
                  "ERMA",
                  "SEATBELT",
                  "IAN",
                  "ENDSUP",
                  "BOOTH",
                  "IRK",
                  "BEEFTACO",
                  "CANNOT",
                  "TRUCKSTOPS",
                  "RENEE",
                  "LASS",
                  "CIS",
                  "ERR",
                  "REAR",
                  "STEIN",
                  "SPIT",
                  "TANS",
                  "ROSEBUSHES",
                  "OCEAN",
                  "PTA",
                  "BOSE",
                  "SKYS",
                  "ULTIMATE",
                  "NOOK",
                  "BORESOME",
                  "INDENT",
                  "ONO",
                  "HOTOIL",
                  "RISER",
                  "GRETA",
                  "JOY",
                  "WAKE",
                  "AKIN",
                  "SANE",
                  "HYDE",
                  "RAT",
                  "UNI"
            ]
      }
}